{
  "type": "GROUP",
"name": "All Requests",
"path": "",
"pathFormatted": "group_missing-name-b06d1",
"stats": {
    "name": "All Requests",
    "numberOfRequests": {
        "total": 84026,
        "ok": 37252,
        "ko": 46774
    },
    "minResponseTime": {
        "total": 0,
        "ok": 0,
        "ko": 0
    },
    "maxResponseTime": {
        "total": 63691,
        "ok": 62352,
        "ko": 63691
    },
    "meanResponseTime": {
        "total": 21738,
        "ok": 8692,
        "ko": 32129
    },
    "standardDeviation": {
        "total": 24594,
        "ok": 16055,
        "ko": 25254
    },
    "percentiles1": {
        "total": 7249,
        "ok": 28,
        "ko": 38655
    },
    "percentiles2": {
        "total": 43547,
        "ok": 9804,
        "ko": 60001
    },
    "percentiles3": {
        "total": 60901,
        "ok": 48515,
        "ko": 61356
    },
    "percentiles4": {
        "total": 61864,
        "ok": 59100,
        "ko": 62242
    },
    "group1": {
    "name": "t < 800 ms",
    "htmlName": "t < 800 ms",
    "count": 24701,
    "percentage": 29
},
    "group2": {
    "name": "800 ms <= t < 1200 ms",
    "htmlName": "t >= 800 ms <br> t < 1200 ms",
    "count": 221,
    "percentage": 0
},
    "group3": {
    "name": "t >= 1200 ms",
    "htmlName": "t >= 1200 ms",
    "count": 12330,
    "percentage": 15
},
    "group4": {
    "name": "failed",
    "htmlName": "failed",
    "count": 46774,
    "percentage": 56
},
    "meanNumberOfRequestsPerSecond": {
        "total": 344.3688524590164,
        "ok": 152.672131147541,
        "ko": 191.69672131147541
    }
},
"contents": {
"req_busca-va-lida-d7f0d": {
        "type": "REQUEST",
        "name": "busca válida",
"path": "busca válida",
"pathFormatted": "req_busca-va-lida-d7f0d",
"stats": {
    "name": "busca válida",
    "numberOfRequests": {
        "total": 9590,
        "ok": 3266,
        "ko": 6324
    },
    "minResponseTime": {
        "total": 0,
        "ok": 1,
        "ko": 0
    },
    "maxResponseTime": {
        "total": 63691,
        "ok": 61970,
        "ko": 63691
    },
    "meanResponseTime": {
        "total": 26879,
        "ok": 12082,
        "ko": 34521
    },
    "standardDeviation": {
        "total": 24980,
        "ok": 17086,
        "ko": 24980
    },
    "percentiles1": {
        "total": 21165,
        "ok": 2021,
        "ko": 39771
    },
    "percentiles2": {
        "total": 60000,
        "ok": 20025,
        "ko": 60003
    },
    "percentiles3": {
        "total": 61310,
        "ok": 50621,
        "ko": 61544
    },
    "percentiles4": {
        "total": 62267,
        "ok": 59553,
        "ko": 62573
    },
    "group1": {
    "name": "t < 800 ms",
    "htmlName": "t < 800 ms",
    "count": 1445,
    "percentage": 15
},
    "group2": {
    "name": "800 ms <= t < 1200 ms",
    "htmlName": "t >= 800 ms <br> t < 1200 ms",
    "count": 78,
    "percentage": 1
},
    "group3": {
    "name": "t >= 1200 ms",
    "htmlName": "t >= 1200 ms",
    "count": 1743,
    "percentage": 18
},
    "group4": {
    "name": "failed",
    "htmlName": "failed",
    "count": 6324,
    "percentage": 66
},
    "meanNumberOfRequestsPerSecond": {
        "total": 39.30327868852459,
        "ok": 13.385245901639344,
        "ko": 25.918032786885245
    }
}
    },"req_criac-a-o-ce502": {
        "type": "REQUEST",
        "name": "criação",
"path": "criação",
"pathFormatted": "req_criac-a-o-ce502",
"stats": {
    "name": "criação",
    "numberOfRequests": {
        "total": 54654,
        "ok": 20494,
        "ko": 34160
    },
    "minResponseTime": {
        "total": 0,
        "ok": 0,
        "ko": 0
    },
    "maxResponseTime": {
        "total": 63553,
        "ok": 62327,
        "ko": 63553
    },
    "meanResponseTime": {
        "total": 23745,
        "ok": 10511,
        "ko": 31684
    },
    "standardDeviation": {
        "total": 24502,
        "ok": 17279,
        "ko": 24765
    },
    "percentiles1": {
        "total": 13504,
        "ok": 48,
        "ko": 37711
    },
    "percentiles2": {
        "total": 44783,
        "ok": 15871,
        "ko": 60000
    },
    "percentiles3": {
        "total": 60905,
        "ok": 51945,
        "ko": 61289
    },
    "percentiles4": {
        "total": 61856,
        "ok": 59246,
        "ko": 62074
    },
    "group1": {
    "name": "t < 800 ms",
    "htmlName": "t < 800 ms",
    "count": 12543,
    "percentage": 23
},
    "group2": {
    "name": "800 ms <= t < 1200 ms",
    "htmlName": "t >= 800 ms <br> t < 1200 ms",
    "count": 103,
    "percentage": 0
},
    "group3": {
    "name": "t >= 1200 ms",
    "htmlName": "t >= 1200 ms",
    "count": 7848,
    "percentage": 14
},
    "group4": {
    "name": "failed",
    "htmlName": "failed",
    "count": 34160,
    "percentage": 63
},
    "meanNumberOfRequestsPerSecond": {
        "total": 223.99180327868854,
        "ok": 83.99180327868852,
        "ko": 140.0
    }
}
    },"req_busca-inva-lida-b5618": {
        "type": "REQUEST",
        "name": "busca inválida",
"path": "busca inválida",
"pathFormatted": "req_busca-inva-lida-b5618",
"stats": {
    "name": "busca inválida",
    "numberOfRequests": {
        "total": 4190,
        "ok": 1839,
        "ko": 2351
    },
    "minResponseTime": {
        "total": 0,
        "ok": 0,
        "ko": 0
    },
    "maxResponseTime": {
        "total": 63473,
        "ok": 61909,
        "ko": 63473
    },
    "meanResponseTime": {
        "total": 22420,
        "ok": 8707,
        "ko": 33147
    },
    "standardDeviation": {
        "total": 24777,
        "ok": 16181,
        "ko": 25043
    },
    "percentiles1": {
        "total": 7959,
        "ok": 11,
        "ko": 39579
    },
    "percentiles2": {
        "total": 44235,
        "ok": 9180,
        "ko": 60000
    },
    "percentiles3": {
        "total": 60811,
        "ok": 48883,
        "ko": 61287
    },
    "percentiles4": {
        "total": 61780,
        "ok": 59162,
        "ko": 61999
    },
    "group1": {
    "name": "t < 800 ms",
    "htmlName": "t < 800 ms",
    "count": 1242,
    "percentage": 30
},
    "group2": {
    "name": "800 ms <= t < 1200 ms",
    "htmlName": "t >= 800 ms <br> t < 1200 ms",
    "count": 12,
    "percentage": 0
},
    "group3": {
    "name": "t >= 1200 ms",
    "htmlName": "t >= 1200 ms",
    "count": 585,
    "percentage": 14
},
    "group4": {
    "name": "failed",
    "htmlName": "failed",
    "count": 2351,
    "percentage": 56
},
    "meanNumberOfRequestsPerSecond": {
        "total": 17.172131147540984,
        "ok": 7.536885245901639,
        "ko": 9.635245901639344
    }
}
    },"req_consulta-5d76b": {
        "type": "REQUEST",
        "name": "consulta",
"path": "consulta",
"pathFormatted": "req_consulta-5d76b",
"stats": {
    "name": "consulta",
    "numberOfRequests": {
        "total": 15592,
        "ok": 11653,
        "ko": 3939
    },
    "minResponseTime": {
        "total": 0,
        "ok": 0,
        "ko": 0
    },
    "maxResponseTime": {
        "total": 63307,
        "ok": 62352,
        "ko": 63307
    },
    "meanResponseTime": {
        "total": 11360,
        "ok": 4541,
        "ko": 31535
    },
    "standardDeviation": {
        "total": 21638,
        "ok": 12228,
        "ko": 29435
    },
    "percentiles1": {
        "total": 20,
        "ok": 5,
        "ko": 60000
    },
    "percentiles2": {
        "total": 4601,
        "ok": 58,
        "ko": 60004
    },
    "percentiles3": {
        "total": 60168,
        "ok": 38318,
        "ko": 61517
    },
    "percentiles4": {
        "total": 61674,
        "ok": 55383,
        "ko": 62731
    },
    "group1": {
    "name": "t < 800 ms",
    "htmlName": "t < 800 ms",
    "count": 9471,
    "percentage": 61
},
    "group2": {
    "name": "800 ms <= t < 1200 ms",
    "htmlName": "t >= 800 ms <br> t < 1200 ms",
    "count": 28,
    "percentage": 0
},
    "group3": {
    "name": "t >= 1200 ms",
    "htmlName": "t >= 1200 ms",
    "count": 2154,
    "percentage": 14
},
    "group4": {
    "name": "failed",
    "htmlName": "failed",
    "count": 3939,
    "percentage": 25
},
    "meanNumberOfRequestsPerSecond": {
        "total": 63.90163934426229,
        "ok": 47.75819672131148,
        "ko": 16.14344262295082
    }
}
    }
}

}